yu_test/__init__.py
yu_test/_nbdev.py
yu_test/core.py
yu_test-0.0.3.dist-info/LICENSE
yu_test-0.0.3.dist-info/METADATA
yu_test-0.0.3.dist-info/WHEEL
yu_test-0.0.3.dist-info/entry_points.txt
yu_test-0.0.3.dist-info/top_level.txt
yu_test-0.0.3.dist-info/RECORD
