Metadata-Version: 2.1
Name: yu-test
Version: 0.0.3
Summary: A description of your project
Home-page: https://github.com/dev/yu_test/tree/master/
Author: Yu Hu
Author-email: nkhuyu@gmail.com
License: Apache Software License 2.0
Keywords: "Test"
Platform: UNKNOWN
Classifier: Development Status :: 3 - Alpha
Classifier: Intended Audience :: Developers
Classifier: License :: OSI Approved :: Apache Software License
Classifier: Natural Language :: English
Classifier: Programming Language :: Python :: 3.6
Classifier: Programming Language :: Python :: 3.7
Classifier: Programming Language :: Python :: 3.8
Requires-Python: >=3.6
